Mem_ref_instr.v
module Mem_ref_instr ( 
		      input wire clk, rst,
		      output reg [11:0]AR,
		      output reg [15:0]AC,
		      output reg [15:0]IR,
		      output reg I,
		      output reg [15:0]DR,
		      output reg [2:0]D,
		      output reg [2:0]current_T_state
	      	      );

reg [12:0]PC;
reg [15:0]M[4095:0];
reg [2:0]state, next_state;

parameter T0=3'b000,
	  T1=3'b001, 
	  T2=3'b010, 
	  T3=3'b011, 
	  T4=3'b100,
	  AND=3'b000, 
	  ADD=3'b001,
	  LDA=3'b010,
	  STA=3'b011,
	  BUN=3'b100,
	  BSA=3'b101,
	  ISZ=3'b110;	  

always@(posedge clk or posedge rst)begin
if(rst)begin
	PC<=12'b0;
	state<=3'b000;
	next_state<=3'b000;
	AR<=12'b0;
	AC<=16'b0;
	IR<=16'b0;
	I<=1'b0;
	DR<=16'b0;
	D<=3'b0;
	current_T_state<=3'b0;
end else begin
	state<=next_state;
	if(state==T1) PC<=PC+1;
	end
end
	
always@(*)begin
	case(state)
		T0:begin
			AR=PC;
			current_T_state=T0;
			next_state=T1;
		end
		
		T1:begin
			IR=M[AR];
			current_T_state=T1;
			next_state=T2;
		end
		
		T2:begin
			AR=IR[11:0];
			I=IR[15];
			current_T_state=T2;
			next_state=T3;
		end
		
		T3:begin
			if(I)begin
					D=IR[14:12];
					$display ("\nAR=%h",AR);
					AR=M[AR];
					$display ("AR=%h",AR);
					
					current_T_state=T3;
					next_state=T4;
				end
				else begin
					D=IR[14:12];
					current_T_state=T3;
					next_state=T4;
				end
		end
		
		T4:begin
			
			case(D)
			AND:begin
				DR = M[AR];
				$display ("\nDR=%h",DR);
				AC = AC & DR;
				$display ("AND operation:\nAC=%h",AC);
				current_T_state=T4;
				next_state=T0;	
			end
			     
			ADD:begin
				DR = M[AR];
				$display ("\nDR=%h",DR);
				AC = AC+DR;
				$display ("ADD operation:\nAC=%h",AC);
				current_T_state=T4;
				next_state=T0;
			end
			     
			LDA:begin
				AC = M[AR];
				$display ("\nAR=%h",AR);
				$display ("LDA operation:\nAC=%h",AC);
				current_T_state=T4;
				next_state=T0;
			end
			     
			STA:begin 
				M[AR] = AC; 
				$display ("\nAR=%h",AR);
				$display ("STA operation: \nM\[AR\]=%h",M[AR]);
				current_T_state=T4;
				next_state=T0;
			end
			
			BUN:begin
				PC=AR;
				$display ("\nBUN operation:\nPC=%h",PC);
				current_T_state=T4;
				next_state=T0;
			end
			
			BSA:begin
				M[AR]=PC;
				$display ("\nBSA operation: \nM\[AR\]=%h",M[AR]);
				AR=AR+1;
				PC=AR;
				current_T_state=T4;
				next_state=T0;
			end
			
			ISZ:begin 
				$display ("\nM\[AR\]=%h",M[AR]);
				M[AR]=M[AR]+1;
				$display ("ISZ operation: \nM\[AR\]=%h",M[AR]);
				if (M[AR]==0)
					PC=PC+1;
				current_T_state=T4;
				next_state=T0;
			end
			endcase
		end
	endcase
end
endmodule

tb_Mem_ref_instr.v
`timescale 1ns/1ps

module tb_Mem_ref_instr;

reg Clk;
reg Rst;
wire [11:0]ar;
wire [15:0]ac;
wire [15:0]ir;
wire i;				      		  
wire [15:0]dr;				      		  
wire [2:0]d;
wire [2:0]state;				      		  						  

Mem_ref_instr DUT(Clk, Rst, ar, ac, ir, i, dr, d, state);

initial begin 
	Clk=1'b0; Rst=1'b1;
	DUT.M[0]=16'b1010000000010100;
	DUT.M[1]=16'b1001000000010101;
	DUT.M[2]=16'b1011000000010110;
	DUT.M[3]=16'b1001000000010111;
	DUT.M[4]=16'b1000000000011000;
	DUT.M[5]=16'b1100000000011011;
	DUT.M[15]=16'b0000000000001010;
	DUT.M[20]=16'b0000000000101000;
	DUT.M[21]=16'b0000000000101001;
	DUT.M[22]=16'b0000000000101010;
	DUT.M[23]=16'b0000000000011010;
	DUT.M[24]=16'b0000000000011001;
	DUT.M[25]=16'b0000000000001100;
	DUT.M[26]=16'b0000000000011110;
	DUT.M[27]=16'b0000000000101011;
	DUT.M[28]=16'b0101000000011101;
	DUT.M[30]=16'b0110000000011111;
	DUT.M[31]=16'b1111111111111111;
	DUT.M[40]=16'b0000000000010100;
	DUT.M[41]=16'b0000000000001010;
	DUT.M[43]=16'b0001000000001111;
	DUT.M[44]=16'b1110000000011110;
	
	#5 Rst=1'b0;
	#500 $finish;
end

initial begin 
	$dumpfile("sim.vcd");
	$dumpvars(0, tb_Mem_ref_instr);
end

always #5 Clk=~Clk;

endmodule

sim.vcd
$date
	Sat Jun 27 01:02:26 2026
$end
$version
	Icarus Verilog
$end
$timescale
	1ps
$end
$scope module tb_Mem_ref_instr $end
$var wire 3 ! state [2:0] $end
$var wire 16 " ir [15:0] $end
$var wire 1 # i $end
$var wire 16 $ dr [15:0] $end
$var wire 3 % d [2:0] $end
$var wire 12 & ar [11:0] $end
$var wire 16 ' ac [15:0] $end
$var reg 1 ( Clk $end
$var reg 1 ) Rst $end
$scope module DUT $end
$var wire 1 ( clk $end
$var wire 1 ) rst $end
$var parameter 3 * ADD $end
$var parameter 3 + AND $end
$var parameter 3 , BSA $end
$var parameter 3 - BUN $end
$var parameter 3 . ISZ $end
$var parameter 3 / LDA $end
$var parameter 3 0 STA $end
$var parameter 3 1 T0 $end
$var parameter 3 2 T1 $end
$var parameter 3 3 T2 $end
$var parameter 3 4 T3 $end
$var parameter 3 5 T4 $end
$var reg 16 6 AC [15:0] $end
$var reg 12 7 AR [11:0] $end
$var reg 3 8 D [2:0] $end
$var reg 16 9 DR [15:0] $end
$var reg 1 # I $end
$var reg 16 : IR [15:0] $end
$var reg 13 ; PC [12:0] $end
$var reg 3 < current_T_state [2:0] $end
$var reg 3 = next_state [2:0] $end
$var reg 3 > state [2:0] $end
$upscope $end
$upscope $end
$enddefinitions $end
$comment Show the parameter values. $end
$dumpall
b100 5
b11 4
b10 3
b1 2
b0 1
b11 0
b10 /
b110 .
b100 -
b101 ,
b0 +
b1 *
$end
#0
$dumpvars
b0 >
b1 =
b0 <
b0 ;
b0 :
b0 9
b0 8
b0 7
b0 6
1)
0(
b0 '
b0 &
b0 %
b0 $
0#
b0 "
b0 !
$end
#5000
b10 =
b1 !
b1 <
b1010000000010100 "
b1010000000010100 :
b1 >
1(
0)
#10000
0(
#15000
b11 =
b10 !
b10 <
1#
b10100 &
b10100 7
b1 ;
b10 >
1(
#20000
0(
#25000
b100 =
b11 !
b11 <
b101000 &
b101000 7
b10 %
b10 8
b11 >
1(
#30000
0(
#35000
b0 =
b100 !
b100 <
b10100 '
b10100 6
b100 >
1(
#40000
0(
#45000
b1 =
b0 !
b0 <
b1 &
b1 7
b0 >
1(
#50000
0(
#55000
b10 =
b1 !
b1 <
b1001000000010101 "
b1001000000010101 :
b1 >
1(
#60000
0(
#65000
b11 =
b10 !
b10 <
b10101 &
b10101 7
b10 ;
b10 >
1(
#70000
0(
#75000
b100 =
b11 !
b11 <
b101001 &
b101001 7
b1 %
b1 8
b11 >
1(
#80000
0(
#85000
b0 =
b100 !
b100 <
b11110 '
b11110 6
b1010 $
b1010 9
b100 >
1(
#90000
0(
#95000
b1 =
b0 !
b0 <
b10 &
b10 7
b0 >
1(
#100000
0(
#105000
b10 =
b1 !
b1 <
b1011000000010110 "
b1011000000010110 :
b1 >
1(
#110000
0(
#115000
b11 =
b10 !
b10 <
b10110 &
b10110 7
b11 ;
b10 >
1(
#120000
0(
#125000
b100 =
b11 !
b11 <
b101010 &
b101010 7
b11 %
b11 8
b11 >
1(
#130000
0(
#135000
b0 =
b100 !
b100 <
b100 >
1(
#140000
0(
#145000
b1 =
b0 !
b0 <
b11 &
b11 7
b0 >
1(
#150000
0(
#155000
b10 =
b1 !
b1 <
b1001000000010111 "
b1001000000010111 :
b1 >
1(
#160000
0(
#165000
b11 =
b10 !
b10 <
b10111 &
b10111 7
b100 ;
b10 >
1(
#170000
0(
#175000
b100 =
b11 !
b11 <
b11010 &
b11010 7
b1 %
b1 8
b11 >
1(
#180000
0(
#185000
b0 =
b100 !
b100 <
b111100 '
b111100 6
b11110 $
b11110 9
b100 >
1(
#190000
0(
#195000
b1 =
b0 !
b0 <
b100 &
b100 7
b0 >
1(
#200000
0(
#205000
b10 =
b1 !
b1 <
b1000000000011000 "
b1000000000011000 :
b1 >
1(
#210000
0(
#215000
b11 =
b10 !
b10 <
b11000 &
b11000 7
b101 ;
b10 >
1(
#220000
0(
#225000
b100 =
b11 !
b11 <
b11001 &
b11001 7
b0 %
b0 8
b11 >
1(
#230000
0(
#235000
b0 =
b100 !
b100 <
b1100 '
b1100 6
b1100 $
b1100 9
b100 >
1(
#240000
0(
#245000
b1 =
b0 !
b0 <
b101 &
b101 7
b0 >
1(
#250000
0(
#255000
b10 =
b1 !
b1 <
b1100000000011011 "
b1100000000011011 :
b1 >
1(
#260000
0(
#265000
b11 =
b10 !
b10 <
b11011 &
b11011 7
b110 ;
b10 >
1(
#270000
0(
#275000
b100 =
b11 !
b11 <
b101011 &
b101011 7
b100 %
b100 8
b11 >
1(
#280000
0(
#285000
b0 =
b100 !
b100 <
b101011 ;
b100 >
1(
#290000
0(
#295000
b1 =
b0 !
b0 <
b0 >
1(
#300000
0(
#305000
b10 =
b1 !
b1 <
b1000000001111 "
b1000000001111 :
b1 >
1(
#310000
0(
#315000
b11 =
b10 !
b10 <
0#
b1111 &
b1111 7
b101100 ;
b10 >
1(
#320000
0(
#325000
b100 =
b11 !
b11 <
b1 %
b1 8
b11 >
1(
#330000
0(
#335000
b0 =
b100 !
b100 <
b10110 '
b10110 6
b1010 $
b1010 9
b100 >
1(
#340000
0(
#345000
b1 =
b0 !
b0 <
b101100 &
b101100 7
b0 >
1(
#350000
0(
#355000
b10 =
b1 !
b1 <
b1110000000011110 "
b1110000000011110 :
b1 >
1(
#360000
0(
#365000
b11 =
b10 !
b10 <
1#
b11110 &
b11110 7
b101101 ;
b10 >
1(
#370000
0(
#375000
b100 =
b11 !
b11 <
b11111 &
b11111 7
b110 %
b110 8
b11 >
1(
#380000
0(
#385000
b0 =
b100 !
b100 <
b101110 ;
b100 >
1(
#390000
0(
#395000
b1 =
b0 !
b0 <
b101110 &
b101110 7
b0 >
1(
#400000
0(
#405000
b10 =
b1 !
b1 <
bx "
bx :
b1 >
1(
#410000
0(
#415000
b11 =
b10 !
b10 <
x#
bx &
bx 7
b101111 ;
b10 >
1(
#420000
0(
#425000
b100 =
b11 !
b11 <
bx %
bx 8
b11 >
1(
#430000
0(
#435000
b100 >
1(
